TBB.py
tbb/__init__.py
tbb/__main__.py
tbb/_api.cp312-win_amd64.pyd
tbb/_api.py
tbb/api.py
tbb/pool.py
tbb/test.py
tbb4py-2022.3.1.dist-info/LICENSE.txt
tbb4py-2022.3.1.dist-info/METADATA
tbb4py-2022.3.1.dist-info/WHEEL
tbb4py-2022.3.1.dist-info/top_level.txt
tbb4py-2022.3.1.dist-info/RECORD
