Metadata-Version: 2.1
Name: tbb4py
Version: 2022.3.1
Summary: Intel® oneAPI Threading Building Blocks (oneTBB)
Home-page: https://github.com/oneapi-src/oneTBB
Author: Intel Corporation
Author-email: scripting@intel.com
License: Intel Simplified Software License
Platform: UNKNOWN
Classifier: Development Status :: 5 - Production/Stable
Classifier: Operating System :: POSIX :: Linux
Classifier: Intended Audience :: Developers
Classifier: Intended Audience :: Education
Classifier: Intended Audience :: System Administrators
Classifier: Intended Audience :: Other Audience
Classifier: Intended Audience :: Science/Research
Classifier: Topic :: Software Development :: Libraries
Classifier: License :: Other/Proprietary License
Requires-Python: >=3.7
License-File: LICENSE.txt
Requires-Dist: tbb (==2022.3.1)
